magsaleanalyser/__init__.py
magsaleanalyser/__main__.py
magsaleanalyser/report_generator.py
magsaleanalyser-0.1.0.dist-info/METADATA
magsaleanalyser-0.1.0.dist-info/WHEEL
magsaleanalyser-0.1.0.dist-info/top_level.txt
magsaleanalyser-0.1.0.dist-info/RECORD
