Metadata-Version: 2.1
Name: magsaleanalyser
Version: 0.1.0
Summary: Application for analyse of financial data
Author-email: Savva Serebriakov <savva08savva08@gmail.com>
License: MIT
Requires-Python: >=3.8
Requires-Dist: pandas==2.2.2
